hub_cep/__init__.py
hub_cep/consts.py
hub_cep/exceptions.py
hub_cep/messages.py
hub_cep/providers.py
hub_cep/zipcode.py
hub_cep-0.0.19.dist-info/METADATA
hub_cep-0.0.19.dist-info/WHEEL
hub_cep-0.0.19.dist-info/top_level.txt
hub_cep-0.0.19.dist-info/RECORD
